<?xml version="1.0" encoding="UTF-8"?>
<tomee>
  <!-- see http://tomee.apache.org/containers-and-resources.html -->
<!--
<Resource id = "My Unmanaged DataSource" type="DataSource">
	JdbcDriver org.hsqldb.jdbcDriver
	JdbcUrl jdbc:hsqldb:file:data/hsqldb/hsqldb
	UserName sa
	Password
	JtaManaged false
</Resource>
-->

 <Resource id="MyJmsResourceAdapter" type="ActiveMQResourceAdapter">
         # Do not start the embedded ActiveMQ broker
         BrokerXmlConfig  =
         ServerUrl = tcp://localhost:61616
 </Resource>
 
 <Resource id="MyJmsConnectionFactory" type="javax.jms.ConnectionFactory">
         ResourceAdapter = MyJmsResourceAdapter
 </Resource>
 
 <Container id="MyJmsMdbContainer" ctype="MESSAGE">
         ResourceAdapter = MyJmsResourceAdapter
 </Container>
 
 <Resource id="FooQueue" type="javax.jms.Queue"/>
 <Resource id="BarTopic" type="javax.jms.Topic"/>


  <!-- activate next line to be able to deploy applications in apps -->
  <Deployments dir="apps" /> 
</tomee>
